[
    { "id" : 1, "time": 1000, "type": "red" , "start_x" :  400 , "start_y" :  0, "end_x" : 400, "end_y" : 400, "move_time" : 3000},
    { "id" : 2, "time": 2000, "type": "red" , "start_x" :  400 , "start_y" :  0, "end_x" : 400, "end_y" : 400, "move_time" : 3000},
    { "id" : 3, "time": 5000, "type": "blue" , "start_x" :  600 , "start_y" :  0, "end_x" : 600, "end_y" : 300, "move_time" : 3000},
    { "id" : 4, "time": 5000, "type": "blue" , "start_x" :  800 , "start_y" :  100, "end_x" : 100, "end_y" : 100, "move_time" : 3000},
    { "id" : 5, "time": 3000, "type": "blue" , "start_x" :  800 , "start_y" :  100, "end_x" : 0, "end_y" : 100, "move_time" : 3000},
    { "id" : 6, "time": 3000, "type": "red" , "start_x" :  800 , "start_y" :  200, "end_x" : 0, "end_y" : 200, "move_time" : 3000}
]